{
  "Ep 10": {
    "as_of": "2026-06-24T15:04:39Z",
    "avg_view_duration_seconds": null,
    "avg_view_percentage": null,
    "comments": null,
    "ctr": null,
    "impressions": null,
    "likes": 9,
    "source": "rss",
    "subscribers_gained": null,
    "views": 671,
    "watch_time_minutes": null,
    "youtube_id": "GzFY-OFvh1Q"
  },
  "Ep 11": {
    "as_of": "2026-06-24T15:04:39Z",
    "avg_view_duration_seconds": null,
    "avg_view_percentage": null,
    "comments": null,
    "ctr": null,
    "impressions": null,
    "likes": 12,
    "source": "rss",
    "subscribers_gained": null,
    "views": 754,
    "watch_time_minutes": null,
    "youtube_id": "UNwzgP3lswo"
  },
  "Ep 12": {
    "as_of": "2026-06-24T15:04:39Z",
    "avg_view_duration_seconds": null,
    "avg_view_percentage": null,
    "comments": null,
    "ctr": null,
    "impressions": null,
    "likes": 6,
    "source": "rss",
    "subscribers_gained": null,
    "views": 820,
    "watch_time_minutes": null,
    "youtube_id": "ZSGZsCHGLYg"
  },
  "Ep 13": {
    "as_of": "2026-06-24T15:04:39Z",
    "avg_view_duration_seconds": null,
    "avg_view_percentage": null,
    "comments": null,
    "ctr": null,
    "impressions": null,
    "likes": 4,
    "source": "rss",
    "subscribers_gained": null,
    "views": 1000,
    "watch_time_minutes": null,
    "youtube_id": "VUJU176o3SI"
  },
  "Ep 14": {
    "as_of": "2026-06-24T15:04:39Z",
    "avg_view_duration_seconds": null,
    "avg_view_percentage": null,
    "comments": null,
    "ctr": null,
    "impressions": null,
    "likes": 3,
    "source": "rss",
    "subscribers_gained": null,
    "views": 531,
    "watch_time_minutes": null,
    "youtube_id": "S8MTwUM56fM"
  },
  "Ep 15": {
    "as_of": "2026-06-24T15:04:39Z",
    "avg_view_duration_seconds": null,
    "avg_view_percentage": null,
    "comments": null,
    "ctr": null,
    "impressions": null,
    "likes": 2,
    "source": "rss",
    "subscribers_gained": null,
    "views": 11,
    "watch_time_minutes": null,
    "youtube_id": "ATRBkdQhIlU"
  },
  "Ep 16": {
    "as_of": "2026-06-24T15:04:39Z",
    "avg_view_duration_seconds": null,
    "avg_view_percentage": null,
    "comments": null,
    "ctr": null,
    "impressions": null,
    "likes": 10,
    "source": "rss",
    "subscribers_gained": null,
    "views": 1093,
    "watch_time_minutes": null,
    "youtube_id": "ut-HJ5JgYTQ"
  },
  "Ep 17": {
    "as_of": "2026-06-24T15:04:39Z",
    "avg_view_duration_seconds": null,
    "avg_view_percentage": null,
    "comments": null,
    "ctr": null,
    "impressions": null,
    "likes": 3,
    "source": "rss",
    "subscribers_gained": null,
    "views": 1047,
    "watch_time_minutes": null,
    "youtube_id": "0zY7L-mL97Y"
  },
  "Ep 3": {
    "as_of": "2026-06-24T15:04:39Z",
    "avg_view_duration_seconds": null,
    "avg_view_percentage": null,
    "comments": null,
    "ctr": null,
    "impressions": null,
    "likes": 15,
    "source": "rss",
    "subscribers_gained": null,
    "views": 1018,
    "watch_time_minutes": null,
    "youtube_id": "k0p1V7T3D9E"
  },
  "Ep 4": {
    "as_of": "2026-06-24T15:04:39Z",
    "avg_view_duration_seconds": null,
    "avg_view_percentage": null,
    "comments": null,
    "ctr": null,
    "impressions": null,
    "likes": 6,
    "source": "rss",
    "subscribers_gained": null,
    "views": 815,
    "watch_time_minutes": null,
    "youtube_id": "TCGGjyA95Pk"
  },
  "Ep 5": {
    "as_of": "2026-06-24T15:04:39Z",
    "avg_view_duration_seconds": null,
    "avg_view_percentage": null,
    "comments": null,
    "ctr": null,
    "impressions": null,
    "likes": 1,
    "source": "rss",
    "subscribers_gained": null,
    "views": 509,
    "watch_time_minutes": null,
    "youtube_id": "Ys1Sq9Z_CNo"
  },
  "Ep 6": {
    "as_of": "2026-06-24T15:04:39Z",
    "avg_view_duration_seconds": null,
    "avg_view_percentage": null,
    "comments": null,
    "ctr": null,
    "impressions": null,
    "likes": 7,
    "source": "rss",
    "subscribers_gained": null,
    "views": 945,
    "watch_time_minutes": null,
    "youtube_id": "3NAOynMjW7g"
  },
  "Ep 7": {
    "as_of": "2026-06-24T15:04:39Z",
    "avg_view_duration_seconds": null,
    "avg_view_percentage": null,
    "comments": null,
    "ctr": null,
    "impressions": null,
    "likes": 7,
    "source": "rss",
    "subscribers_gained": null,
    "views": 718,
    "watch_time_minutes": null,
    "youtube_id": "fgNfzyllti8"
  },
  "Ep 8": {
    "as_of": "2026-06-24T15:04:39Z",
    "avg_view_duration_seconds": null,
    "avg_view_percentage": null,
    "comments": null,
    "ctr": null,
    "impressions": null,
    "likes": 7,
    "source": "rss",
    "subscribers_gained": null,
    "views": 931,
    "watch_time_minutes": null,
    "youtube_id": "l8LjnU7ppiY"
  },
  "fable5": {
    "as_of": "2026-06-24T15:04:39Z",
    "avg_view_duration_seconds": null,
    "avg_view_percentage": null,
    "comments": null,
    "ctr": null,
    "impressions": null,
    "likes": 3,
    "source": "rss",
    "subscribers_gained": null,
    "views": 359,
    "watch_time_minutes": null,
    "youtube_id": "8AoM8EP-wYY"
  }
}
